example777/__init__.py
example777/math_funcs.py
example777-0.1.0.dist-info/METADATA
example777-0.1.0.dist-info/WHEEL
example777-0.1.0.dist-info/top_level.txt
example777-0.1.0.dist-info/RECORD
