Metadata-Version: 2.1
Name: example777
Version: 0.1.0
Summary: Test package to demonstrate how to build packages
Author: M.O.
License: MIT
